{
  "project_info": {
    "project_number": "1017983475561",
    "project_id": "weatherapp-f9e80",
    "storage_bucket": "weatherapp-f9e80.firebasestorage.app"
  },
  "client": [
    {
      "client_info": {
        "mobilesdk_app_id": "1:1017983475561:android:016207299a668f150927f8",
        "android_client_info": {
          "package_name": "com.example.weatherapp"
        }
      },
      "oauth_client": [],
      "api_key": [
        {
          "current_key": "AIzaSyDaCaocZdeES89SP8mK8plWocjzG_aHQx8"
        }
      ],
      "services": {
        "appinvite_service": {
          "other_platform_oauth_client": []
        }
      }
    }
  ],
  "configuration_version": "1"
}